[
    {
      "title": "Welcome to HQ!",
      "text": "This is your default landing page.",
      "buttons": [
        { "text": "Next", "action": "next" }
      ]
    },
    {
      "title": "The sidebar",
      "text": "The sidebar shows your some quick access links for your apps.",
      "attachTo": { "element": ".app-sidebar", "on": "right" },      
      "onShow": "expandSidebar",
      "buttons": [
        {"text":"Back", "action": "back" },
        {"text":"Next", "action": "next" }
      ]
    },
    {
      "title": "Light/Dark mode toggle",
      "text": "You can toggle light/dark mode using these buttons. Try toggling between light/dark modes by clicking on them.",
      "attachTo": { "element": "#bd-theme", "on": "right" },     
      "buttons": [
        {"text":"Back", "action": "back" },
        {"text":"Next", "action": "next" }
      ]
    },
    {
      "title": "Pinned Apps",
      "text": "Your pinned apps are shown under this menu",
      "attachTo": { "element": "#pinned-apps", "on": "right" },     
      "buttons": [
        {"text":"Back", "action": "back" },
        {"text":"Next", "action": "next" }
      ]
    },
    {
      "title": "Featured Apps",
      "text": "Your featured apps are shown here.",
      "attachTo": { "element": "#featured-apps", "on": "right" },     
      "buttons": [
        {"text":"Back", "action": "back" },
        {"text":"Next", "action": "next" }
      ]
    },
    {
      "title": "Manage apps",
      "text": "You can install more apps, pin them, feature them on the sidebar using this link.",
      "attachTo": { "element": "#manage-apps", "on": "right" },     
      "buttons": [
        {"text":"Back", "action": "back" },
        {"text":"Next", "action": "next" }
      ]
    },
    {
      "title": "The Header",
      "text": "The header contains buttons for toggling the sidebar visibility, your current location, and other quick links.",
      "attachTo": { "element": ".app-header", "on": "bottom" },     
      "onShow": "collapseSidebar",
      "buttons": [
        {"text":"Back", "action": "back" },
        {"text":"Next", "action": "next" }
      ]

    },
    {
      "title": "Toggle Sidebar",
      "text": "The sidebar can be toggled between expanded/mini version and on smaller screen the sidebar is hidden and can be accessed using this button.",
      "attachTo": { "element": "#toggle-sidebar", "on": "bottom" },     
      "buttons": [
        {"text":"Back", "action": "back" },
        {"text":"Next", "action": "next" }
      ]
    },
    {
      "title": "Search button",
      "text": "You can quickly search contacts, hashtags, forums and help files.",
      "attachTo": { "element": "#nav-search-btn", "on": "bottom" },     
      "buttons": [
        {"text":"Back", "action": "back" },
        {"text":"Next", "action": "next" }
      ]
    },
    {
      "title": "Notifications",
      "text": "Your notifications can be accessed using this dropdown.",
      "attachTo": { "element": "#notifications-btn-1", "on": "bottom" },     
      "buttons": [
        {"text":"Back", "action": "back" },
        {"text":"Next", "action": "next" }
      ]
    },
    {
      "title": "User Menu",
      "text": "You can view/edit your profile(s), switch to other channels, view settings or logout from here",
      "attachTo": { "element": ".user-menu", "on": "bottom" },     
      "buttons": [
        {"text":"Back", "action": "back" },
        {"text":"Next", "action": "next" }
      ]
    },
    {
      "title": "Activity Overview",
      "text": "Your recently uploaded photos, posts, webpages, wiki pages, etc are shown here.",
      "attachTo": { "element": "#channel-activities", "on": "right" },     
      "buttons": [
        {"text":"Back", "action": "back" },
        {"text":"Next", "action": "next" }
      ]
    },
    {
      "title": "Messages Widget",
      "text": "This widget shows you recent posts from your network, direct messages, starred posts(if enabled), saved folders(if enabled) and notification.",
      "attachTo": { "element": "#messages-widget", "on": "left" },     
      "onShow": "toggleOffcanvas",
      "buttons": [
        {"text":"Back", "action": "back" },
        {"text":"Close", "action": "cancel" }
      ]
    }
 ]
